json2daisy/__init__.py
json2daisy/__main__.py
json2daisy/json2daisy.py
json2daisy/resources/LICENSE
json2daisy/resources/component_defs.json
json2daisy/resources/component_defs_patchsm.json
json2daisy/resources/component_defs_petalsm.json
json2daisy/resources/field.json
json2daisy/resources/patch.json
json2daisy/resources/patch_init.json
json2daisy/resources/petal.json
json2daisy/resources/petal_125b_sm.json
json2daisy/resources/pod.json
json2daisy/templates/daisy.h
json2daisy-0.4.2.dist-info/LICENSE
json2daisy-0.4.2.dist-info/METADATA
json2daisy-0.4.2.dist-info/WHEEL
json2daisy-0.4.2.dist-info/top_level.txt
json2daisy-0.4.2.dist-info/RECORD
