Metadata-Version: 2.1
Name: json2daisy
Version: 0.4.2
Summary: A utility for generating Daisy board support files from JSON descriptions
Home-page: https://github.com/electro-smith/json2daisy
Author: Electrosmith
Author-email: shensley@electro-smith.com
License: MIT
Project-URL: Bug Tracker, https://github.com/electro-smith/json2daisy/issues
Classifier: Programming Language :: Python :: 3
Classifier: License :: OSI Approved :: MIT License
Classifier: Operating System :: OS Independent
Classifier: Programming Language :: Python :: 3.7
Classifier: Programming Language :: Python :: 3.8
Classifier: Programming Language :: Python :: 3.9
Requires-Python: >=3.7
License-File: LICENSE
Requires-Dist: Jinja2 (>=2.11)
